rpa_temu/__init__.py
rpa_temu/api/BaseApi.py
rpa_temu/api/__init__.py
rpa_temu/api/order/BillApi.py
rpa_temu/api/order/RefundRetApi.py
rpa_temu/api/order/ViolationApi.py
rpa_temu/api/order/__init__.py
rpa_temu/api/shop/AdsApi.py
rpa_temu/api/shop/AmountApi.py
rpa_temu/api/shop/BillDetailApi.py
rpa_temu/api/shop/DeliveryLabelApi.py
rpa_temu/api/shop/RefundLabelApi.py
rpa_temu/api/shop/ShopApi.py
rpa_temu/api/shop/__init__.py
rpa_temu/cmd/__init__.py
rpa_temu/cmd/order/Bill.py
rpa_temu/cmd/order/Refund.py
rpa_temu/cmd/order/Violation.py
rpa_temu/cmd/order/__init__.py
rpa_temu/cmd/shop/Ads.py
rpa_temu/cmd/shop/Amount.py
rpa_temu/cmd/shop/BillDetail.py
rpa_temu/cmd/shop/DeliveryLabel.py
rpa_temu/cmd/shop/RefundLabel.py
rpa_temu/cmd/shop/__init__.py
rpa_temu/service/TemuService.py
rpa_temu/service/__init__.py
rpa_temu-1.0.10.dist-info/LICENSE
rpa_temu-1.0.10.dist-info/METADATA
rpa_temu-1.0.10.dist-info/WHEEL
rpa_temu-1.0.10.dist-info/top_level.txt
rpa_temu-1.0.10.dist-info/RECORD
